[
  {
    "name": "Ishan Saraf",
    "title": "Software Developer",
    "email": "ishaansaraf03@gmail.com",
    "phone": "+917503094360",
    "location": "Delhi, India",
    "tagline": "I'm a Software Engineer with a primary focus on Full-Stack Development and creating seamless digital experiences.",
    "about": "💻 I'm a Software Engineer who enjoys Full-Stack Development and building smooth digital experiences.\n✨ I like turning ideas into interactive, user-friendly applications that look good and work well.\n🎨 I pay attention to details and solve problems to create useful and efficient solutions.",
    "profile_picture": "https://media.licdn.com/dms/image/v2/D5603AQHuXfbigy-4Bg/profile-displayphoto-shrink_800_800/B56ZOgaRDhGgAc-/0/1733563061433?e=1746057600&v=beta&t=EMbRXqd4oZ7M8RVM8DuZwH1ZDnQF57Xt7iuoNkDVJR0"
  }
]
